{
    "name": "Shivanshi",
    "title": "Full Stack Developer",
    "intro": "Learning Enthusiast!",
    "skills": [{
            "title": "HTML",
            "rating": "80"
        },
        {
            "title": "CSS",
            "rating": "80"
        },
        {
            "title": "JavaScript",
            "rating": "75"
        },{
            "title": "Java",
            "rating": "85"
        },{
            "title": "C++",
            "rating": "78"
        },{
            "title": "C",
            "rating": "70"
        }
    ],
    "contact": {
        "location": "Chitkara University",
        "phone": "8528701052",
        "email": "shivanshi171764.cse@chitkara.edu.in"
    }
}
